penn/__init__.py
penn/base.py
penn/calendar3year.py
penn/dining.py
penn/directory.py
penn/fitness.py
penn/laundry.py
penn/libraries.py
penn/map.py
penn/news.py
penn/registrar.py
penn/studyspaces.py
penn/transit.py
penn/wharton.py
penn/data/laundry.csv
PennSDK-1.8.9.dist-info/AUTHORS.rst
PennSDK-1.8.9.dist-info/LICENSE.txt
PennSDK-1.8.9.dist-info/METADATA
PennSDK-1.8.9.dist-info/WHEEL
PennSDK-1.8.9.dist-info/top_level.txt
PennSDK-1.8.9.dist-info/RECORD
