Metadata-Version: 2.1
Name: PennSDK
Version: 1.8.9
Summary: Python tools for building Penn-related applications
Home-page: https://github.com/pennlabs/penn-sdk-python
Author: Penn Labs
Author-email: admin@pennlabs.org
License: MIT
Platform: UNKNOWN
Requires-Dist: nameparser (==0.5.6)
Requires-Dist: requests (==2.20.0)
Requires-Dist: beautifulsoup4 (==4.6.0)
Requires-Dist: html5lib (==1.0.1)
